{"0": [["razko\u013a\u02c7en", []], "Z"], "1": [["za\u013a\u013emukati", ["a", "e", "i", "b", "c", "s", "o", "u", "l", "p", "r", "\u0161", "t", "v", "m", "n"]], "X"], "2": [["diaklaza", []], "Z"], "3": [["gola\u013a\u013eijada", []], "Z"], "4": [["preostuden", []], "Z"], "5": [["kolobencati", []], "Z"], "6": [["filmiziran", []], "Z"], "7": [["zbu\u00e4\u0165ati", []], "Z"], "8": [["avtome\u013a\u02c7alnik", []], "Z"], "9": [["olj\u00e4\u0165ica", []], "Z"], "10": [["sol\u013a\u013eefrenija", []], "Z"], "11": [["zunajaktivnost", []], "Z"], "12": [["mo\u00e4\u0165nopuhast", []], "Z"], "13": [["intrapalpebralen", []], "Z"], "14": [["zrevolucionirati", []], "Z"], "15": [["farmacevtka", []], "Z"], "16": [["protokultura", []], "Z"], "17": [["psevdomembrana", []], "Z"], "18": [["balneomedicinski", []], "Z"], "19": [["avstroogski", ["a", "\u0161", "\u010d", "\u017e", "l", "m", "n", "i", "u", "r", "e", "w", "q", "x"]], "X"], "20": [["oblikovnost", []], "Z"]}